feature_lists/__init__.py
feature_lists/feature_properties.py
feature_lists-0.1.2.dist-info/LICENSE
feature_lists-0.1.2.dist-info/METADATA
feature_lists-0.1.2.dist-info/WHEEL
feature_lists-0.1.2.dist-info/top_level.txt
feature_lists-0.1.2.dist-info/RECORD
